neutrons-0.0.3.dist-info/METADATA
neutrons-0.0.3.dist-info/WHEEL
neutrons-0.0.3.dist-info/license_files/LICENSE
neutrons/__init__.py
neutrons/neutrons.cpython-311-darwin.so
neutrons-0.0.3.dist-info/RECORD
