Metadata-Version: 2.1
Name: neutrons
Version: 0.0.3
Classifier: Programming Language :: Rust
Classifier: Programming Language :: Python :: Implementation :: CPython
Classifier: Programming Language :: Python :: Implementation :: PyPy
License-File: LICENSE
Summary: Neutron transport simulation.
Author: Freddy Wordingham <freddy@digilab.co.uk>
Author-email: Freddy Wordingham <freddy@digilab.co.uk>
Requires-Python: >=3.7
